jsonschema_to_sqlalchemy_flask/__init__.py
jsonschema_to_sqlalchemy_flask/version.py
jsonschema_to_sqlalchemy_flask/src/__init__.py
jsonschema_to_sqlalchemy_flask/src/convert_from_json_schema.py
jsonschema_to_sqlalchemy_flask/src/convert_to_json_dump.py
jsonschema_to_sqlalchemy_flask/src/convert_to_json_loader.py
jsonschema_to_sqlalchemy_flask/src/convert_to_sqlalchemy_flask.py
jsonschema_to_sqlalchemy_flask/src/convert_to_unique_name_list_getter.py
jsonschema_to_sqlalchemy_flask/src/file_handling.py
jsonschema_to_sqlalchemy_flask/src/get_order.py
jsonschema_to_sqlalchemy_flask/templates/create_from_json_template.mustache
jsonschema_to_sqlalchemy_flask/templates/dump_to_json_template.mustache
jsonschema_to_sqlalchemy_flask/templates/flask_template.mustache
jsonschema_to_sqlalchemy_flask/templates/footer.py
jsonschema_to_sqlalchemy_flask/templates/get_unique_name_list_template.mustache
jsonschema_to_sqlalchemy_flask/templates/header.py
jsonschema_to_sqlalchemy_flask/templates/middle.py
jsonschema_to_sqlalchemy_flask/test/__init__.py
jsonschema_to_sqlalchemy_flask/test/jsonschema_to_sqlalchemy_flask_test.py
jsonschema_to_sqlalchemy_flask/test/data/test1.json
jsonschema_to_sqlalchemy_flask/test/data/test1.schema.json
jsonschema_to_sqlalchemy_flask/test/data/test2.json
jsonschema_to_sqlalchemy_flask/test/data/test2.schema.json
jsonschema_to_sqlalchemy_flask/test/data/test_unique_name_lists.json
jsonschema_to_sqlalchemy_flask/test/expected_output/__init__.py
jsonschema_to_sqlalchemy_flask/test/expected_output/converted.json
jsonschema_to_sqlalchemy_flask/test/expected_output/create_from_json.py
jsonschema_to_sqlalchemy_flask/test/expected_output/dump_to_json.py
jsonschema_to_sqlalchemy_flask/test/expected_output/get_unique_name_list.py
jsonschema_to_sqlalchemy_flask/test/expected_output/result.py
jsonschema_to_sqlalchemy_flask/test/helper/create_database.py
jsonschema_to_sqlalchemy_flask-0.1.4.dist-info/LICENSE
jsonschema_to_sqlalchemy_flask-0.1.4.dist-info/METADATA
jsonschema_to_sqlalchemy_flask-0.1.4.dist-info/WHEEL
jsonschema_to_sqlalchemy_flask-0.1.4.dist-info/top_level.txt
jsonschema_to_sqlalchemy_flask-0.1.4.dist-info/RECORD
