Metadata-Version: 2.1
Name: jsonschema-to-sqlalchemy-flask
Version: 0.1.4
Summary: A package to convert json schema data to a sqlachemy flask file
License: MIT
Keywords: jsonschema,sqlalchemy,flask
Classifier: License :: OSI Approved :: MIT License
Classifier: Development Status :: 3 - Alpha
Classifier: Operating System :: POSIX :: Linux
Classifier: Programming Language :: Python :: 3.10
Requires-Python: >=3.10
License-File: LICENSE
Requires-Dist: chevron
Requires-Dist: pytest
Requires-Dist: Flask
Requires-Dist: Flask-SQLAlchemy
Requires-Dist: flask-admin
